datapizza/modules/rerankers/together/__init__.py
datapizza/modules/rerankers/together/together_reranker.py
datapizza_ai_rerankers_together-0.0.3.dist-info/METADATA
datapizza_ai_rerankers_together-0.0.3.dist-info/WHEEL
datapizza_ai_rerankers_together-0.0.3.dist-info/RECORD
